{
    "classification": "oobb",
    "type": "part",
    "size": "oobb",
    "color": "",
    "description_main": "bunting_alphabet_05_01_ex_A",
    "description_extra": "",
    "manufacturer": "",
    "part_number": "",
    "make_files": true,
    "short_name": "",
    "distributors": [],
    "classification_upper": "OOBB",
    "classification_capital": "Oobb",
    "classification_first_letter": "o",
    "classification_first_letter_upper": "O",
    "type_upper": "PART",
    "type_capital": "Part",
    "type_first_letter": "p",
    "type_first_letter_upper": "P",
    "size_upper": "OOBB",
    "size_capital": "Oobb",
    "size_first_letter": "o",
    "size_first_letter_upper": "O",
    "color_upper": "",
    "color_capital": "",
    "color_first_letter": "",
    "color_first_letter_upper": "",
    "description_main_upper": "BUNTING_ALPHABET_05_01_EX_A",
    "description_main_capital": "Bunting Alphabet 05 01 Ex A",
    "description_main_first_letter": "b",
    "description_main_first_letter_upper": "B",
    "description_extra_upper": "",
    "description_extra_capital": "",
    "description_extra_first_letter": "",
    "description_extra_first_letter_upper": "",
    "manufacturer_upper": "",
    "manufacturer_capital": "",
    "manufacturer_first_letter": "",
    "manufacturer_first_letter_upper": "",
    "part_number_upper": "",
    "part_number_capital": "",
    "part_number_first_letter": "",
    "part_number_first_letter_upper": "",
    "id": "oobb_part_oobb_bunting_alphabet_05_01_ex_A",
    "id_no_class": "part_bunting_alphabet_05_01_ex_A",
    "id_no_type": "bunting_alphabet_05_01_ex_A",
    "id_no_size": "bunting_alphabet_05_01_ex_A",
    "oomp_key": "oomp_oobb_part_oobb_bunting_alphabet_05_01_ex_A",
    "github_link": "https://github.com/oomlout/oomlout_oomp_part_src/tree/main/parts/oobb_part_oobb_bunting_alphabet_05_01_ex_A/working",
    "directory": "parts/oobb_part_oobb_bunting_alphabet_05_01_ex_A",
    "name": "Oobb Part Oobb Bunting Alphabet 05 01 Ex A",
    "name_no_class": "Part Bunting Alphabet 05 01 Ex A",
    "name_no_type": "Bunting Alphabet 05 01 Ex A",
    "name_no_size": "Bunting Alphabet 05 01 Ex A",
    "short_code": "ob",
    "short_code_upper": "OB",
    "manufacturers": [],
    "md5": "bfe0a23294e1775786e621da9387e5cc",
    "md5_5": "bfe0a",
    "md5_5_upper": "BFE0A",
    "md5_6": "bfe0a2",
    "md5_6_upper": "BFE0A2",
    "md5_6_alpha": "7hiua",
    "md5_6_alpha_upper": "7HIUA",
    "md5_10": "bfe0a23294",
    "md5_10_upper": "BFE0A23294",
    "oomp_word": "egg ship violin",
    "oomp_word_list": [
        "egg",
        "ship",
        "violin"
    ],
    "oomp_word_emoji": ":egg: :ship: :violin:",
    "oomp_word_emoji_list": [
        ":egg:",
        ":ship:",
        ":violin:"
    ],
    "size_only_numbers": "",
    "size_only_numbers_no_zeros": "",
    "description_only_numbers": "0501",
    "description_only_numbers_short": "501",
    "name_no_size_short": "Bunting Alphabet 05 01 Ex A",
    "description_or_color": "501",
    "description_or_color_upper": "501",
    "markdown_full": "[oobb_part_oobb_bunting_alphabet_05_01_ex_A](https://github.com/oomlout/oomlout_oomp_part_src/tree/main/parts/oobb_part_oobb_bunting_alphabet_05_01_ex_A/working)<br>[ob](https://github.com/oomlout/oomlout_oomp_part_src/tree/main/parts/oobb_part_oobb_bunting_alphabet_05_01_ex_A/working)<br>[Oobb Part Oobb Bunting Alphabet 05 01 Ex A](https://github.com/oomlout/oomlout_oomp_part_src/tree/main/parts/oobb_part_oobb_bunting_alphabet_05_01_ex_A/working)<br><br>",
    "markdown_short": "[oobb_part_oobb_bunting_alphabet_05_01_ex_A](https://github.com/oomlout/oomlout_oomp_part_src/tree/main/parts/oobb_part_oobb_bunting_alphabet_05_01_ex_A/working)<br><br>"
}