{
    "classification": "oobb",
    "type": "part",
    "size": "tray",
    "color": "",
    "description_main": "03_06_18",
    "description_extra": "",
    "manufacturer": "",
    "part_number": "",
    "make_files": true,
    "short_name": "",
    "distributors": [],
    "classification_upper": "OOBB",
    "classification_capital": "Oobb",
    "classification_first_letter": "o",
    "classification_first_letter_upper": "O",
    "type_upper": "PART",
    "type_capital": "Part",
    "type_first_letter": "p",
    "type_first_letter_upper": "P",
    "size_upper": "TRAY",
    "size_capital": "Tray",
    "size_first_letter": "t",
    "size_first_letter_upper": "T",
    "color_upper": "",
    "color_capital": "",
    "color_first_letter": "",
    "color_first_letter_upper": "",
    "description_main_upper": "03_06_18",
    "description_main_capital": "03 06.18",
    "description_main_first_letter": "0",
    "description_main_first_letter_upper": "0",
    "description_extra_upper": "",
    "description_extra_capital": "",
    "description_extra_first_letter": "",
    "description_extra_first_letter_upper": "",
    "manufacturer_upper": "",
    "manufacturer_capital": "",
    "manufacturer_first_letter": "",
    "manufacturer_first_letter_upper": "",
    "part_number_upper": "",
    "part_number_capital": "",
    "part_number_first_letter": "",
    "part_number_first_letter_upper": "",
    "id": "oobb_part_tray_03_06_18",
    "id_no_class": "part_tray_03_06_18",
    "id_no_type": "tray_03_06_18",
    "id_no_size": "03_06_18",
    "oomp_key": "oomp_oobb_part_tray_03_06_18",
    "github_link": "https://github.com/oomlout/oomlout_oomp_part_src/tree/main/parts/oobb_part_tray_03_06_18/working",
    "directory": "parts/oobb_part_tray_03_06_18",
    "name": "Oobb Part Tray 03 06 18",
    "name_no_class": "Part Tray 03 06 18",
    "name_no_type": "Tray 03 06 18",
    "name_no_size": "03 06 18",
    "short_code": "",
    "short_code_upper": "",
    "manufacturers": [],
    "md5": "e9e85e14e3e7b3b8a287d09848c088a8",
    "md5_5": "e9e85",
    "md5_5_upper": "E9E85",
    "md5_6": "e9e85e",
    "md5_6_upper": "E9E85E",
    "md5_6_alpha": "94k7y",
    "md5_6_alpha_upper": "94K7Y",
    "md5_10": "e9e85e14e3",
    "md5_10_upper": "E9E85E14E3",
    "oomp_word": "bike tram crocodile",
    "oomp_word_list": [
        "bike",
        "tram",
        "crocodile"
    ],
    "oomp_word_emoji": ":bike: :tram: :crocodile:",
    "oomp_word_emoji_list": [
        ":bike:",
        ":tram:",
        ":crocodile:"
    ],
    "size_only_numbers": "",
    "size_only_numbers_no_zeros": "",
    "description_only_numbers": "030618",
    "description_only_numbers_short": "31k",
    "name_no_size_short": "03 06 18",
    "description_or_color": "31k",
    "description_or_color_upper": "31K",
    "markdown_full": "[oobb_part_tray_03_06_18](https://github.com/oomlout/oomlout_oomp_part_src/tree/main/parts/oobb_part_tray_03_06_18/working)<br>[](https://github.com/oomlout/oomlout_oomp_part_src/tree/main/parts/oobb_part_tray_03_06_18/working)<br>[Oobb Part Tray 03 06 18](https://github.com/oomlout/oomlout_oomp_part_src/tree/main/parts/oobb_part_tray_03_06_18/working)<br><br>",
    "markdown_short": "[oobb_part_tray_03_06_18](https://github.com/oomlout/oomlout_oomp_part_src/tree/main/parts/oobb_part_tray_03_06_18/working)<br><br>"
}