{
    "classification": "oobb",
    "type": "part",
    "size": "tray_thin",
    "color": "",
    "description_main": "10_02_30",
    "description_extra": "",
    "manufacturer": "",
    "part_number": "",
    "make_files": true,
    "short_name": "",
    "distributors": [],
    "classification_upper": "OOBB",
    "classification_capital": "Oobb",
    "classification_first_letter": "o",
    "classification_first_letter_upper": "O",
    "type_upper": "PART",
    "type_capital": "Part",
    "type_first_letter": "p",
    "type_first_letter_upper": "P",
    "size_upper": "TRAY_THIN",
    "size_capital": "Tray Thin",
    "size_first_letter": "t",
    "size_first_letter_upper": "T",
    "color_upper": "",
    "color_capital": "",
    "color_first_letter": "",
    "color_first_letter_upper": "",
    "description_main_upper": "10_02_30",
    "description_main_capital": "10 02.30",
    "description_main_first_letter": "1",
    "description_main_first_letter_upper": "1",
    "description_extra_upper": "",
    "description_extra_capital": "",
    "description_extra_first_letter": "",
    "description_extra_first_letter_upper": "",
    "manufacturer_upper": "",
    "manufacturer_capital": "",
    "manufacturer_first_letter": "",
    "manufacturer_first_letter_upper": "",
    "part_number_upper": "",
    "part_number_capital": "",
    "part_number_first_letter": "",
    "part_number_first_letter_upper": "",
    "id": "oobb_part_tray_thin_10_02_30",
    "id_no_class": "part_tray_thin_10_02_30",
    "id_no_type": "tray_thin_10_02_30",
    "id_no_size": "10_02_30",
    "oomp_key": "oomp_oobb_part_tray_thin_10_02_30",
    "github_link": "https://github.com/oomlout/oomlout_oomp_part_src/tree/main/parts/oobb_part_tray_thin_10_02_30/working",
    "directory": "parts/oobb_part_tray_thin_10_02_30",
    "name": "Oobb Part Tray Thin 10 02 30",
    "name_no_class": "Part Tray Thin 10 02 30",
    "name_no_type": "Tray Thin 10 02 30",
    "name_no_size": "10 02 30",
    "short_code": "",
    "short_code_upper": "",
    "manufacturers": [],
    "md5": "c586e90ac189584dd12e4ea1057d968f",
    "md5_5": "c586e",
    "md5_5_upper": "C586E",
    "md5_6": "c586e9",
    "md5_6_upper": "C586E9",
    "md5_6_alpha": "7pgix",
    "md5_6_alpha_upper": "7PGIX",
    "md5_10": "c586e90ac1",
    "md5_10_upper": "C586E90AC1",
    "oomp_word": "candy bath bike",
    "oomp_word_list": [
        "candy",
        "bath",
        "bike"
    ],
    "oomp_word_emoji": ":candy: :bath: :bike:",
    "oomp_word_emoji_list": [
        ":candy:",
        ":bath:",
        ":bike:"
    ],
    "size_only_numbers": "",
    "size_only_numbers_no_zeros": "",
    "description_only_numbers": "100230",
    "description_only_numbers_short": "100k",
    "name_no_size_short": "10 02 30",
    "description_or_color": "100k",
    "description_or_color_upper": "100K",
    "markdown_full": "[oobb_part_tray_thin_10_02_30](https://github.com/oomlout/oomlout_oomp_part_src/tree/main/parts/oobb_part_tray_thin_10_02_30/working)<br>[](https://github.com/oomlout/oomlout_oomp_part_src/tree/main/parts/oobb_part_tray_thin_10_02_30/working)<br>[Oobb Part Tray Thin 10 02 30](https://github.com/oomlout/oomlout_oomp_part_src/tree/main/parts/oobb_part_tray_thin_10_02_30/working)<br><br>",
    "markdown_short": "[oobb_part_tray_thin_10_02_30](https://github.com/oomlout/oomlout_oomp_part_src/tree/main/parts/oobb_part_tray_thin_10_02_30/working)<br><br>"
}