{
    "classification": "oobb",
    "type": "part",
    "size": "oobb",
    "color": "",
    "description_main": "tray_vertical_08_06_12",
    "description_extra": "",
    "manufacturer": "",
    "part_number": "",
    "make_files": true,
    "short_name": "",
    "distributors": [],
    "classification_upper": "OOBB",
    "classification_capital": "Oobb",
    "classification_first_letter": "o",
    "classification_first_letter_upper": "O",
    "type_upper": "PART",
    "type_capital": "Part",
    "type_first_letter": "p",
    "type_first_letter_upper": "P",
    "size_upper": "OOBB",
    "size_capital": "Oobb",
    "size_first_letter": "o",
    "size_first_letter_upper": "O",
    "color_upper": "",
    "color_capital": "",
    "color_first_letter": "",
    "color_first_letter_upper": "",
    "description_main_upper": "TRAY_VERTICAL_08_06_12",
    "description_main_capital": "Tray Vertical 08 06.12",
    "description_main_first_letter": "t",
    "description_main_first_letter_upper": "T",
    "description_extra_upper": "",
    "description_extra_capital": "",
    "description_extra_first_letter": "",
    "description_extra_first_letter_upper": "",
    "manufacturer_upper": "",
    "manufacturer_capital": "",
    "manufacturer_first_letter": "",
    "manufacturer_first_letter_upper": "",
    "part_number_upper": "",
    "part_number_capital": "",
    "part_number_first_letter": "",
    "part_number_first_letter_upper": "",
    "id": "oobb_part_oobb_tray_vertical_08_06_12",
    "id_no_class": "part_tray_vertical_08_06_12",
    "id_no_type": "tray_vertical_08_06_12",
    "id_no_size": "tray_vertical_08_06_12",
    "oomp_key": "oomp_oobb_part_oobb_tray_vertical_08_06_12",
    "github_link": "https://github.com/oomlout/oomlout_oomp_part_src/tree/main/parts/oobb_part_oobb_tray_vertical_08_06_12/working",
    "directory": "parts/oobb_part_oobb_tray_vertical_08_06_12",
    "name": "Oobb Part Oobb Tray Vertical 08 06 12",
    "name_no_class": "Part Tray Vertical 08 06 12",
    "name_no_type": "Tray Vertical 08 06 12",
    "name_no_size": "Tray Vertical 08 06 12",
    "short_code": "ob",
    "short_code_upper": "OB",
    "manufacturers": [],
    "md5": "1bc8af4916dc56e99564e0667af6acfa",
    "md5_5": "1bc8a",
    "md5_5_upper": "1BC8A",
    "md5_6": "1bc8af",
    "md5_6_upper": "1BC8AF",
    "md5_6_alpha": "130z3",
    "md5_6_alpha_upper": "130Z3",
    "md5_10": "1bc8af4916",
    "md5_10_upper": "1BC8AF4916",
    "oomp_word": "muscle apple tophat",
    "oomp_word_list": [
        "muscle",
        "apple",
        "tophat"
    ],
    "oomp_word_emoji": ":muscle: :apple: :tophat:",
    "oomp_word_emoji_list": [
        ":muscle:",
        ":apple:",
        ":tophat:"
    ],
    "size_only_numbers": "",
    "size_only_numbers_no_zeros": "",
    "description_only_numbers": "080612",
    "description_only_numbers_short": "81k",
    "name_no_size_short": "Tray Vertical 08 06 12",
    "description_or_color": "81k",
    "description_or_color_upper": "81K",
    "markdown_full": "[oobb_part_oobb_tray_vertical_08_06_12](https://github.com/oomlout/oomlout_oomp_part_src/tree/main/parts/oobb_part_oobb_tray_vertical_08_06_12/working)<br>[ob](https://github.com/oomlout/oomlout_oomp_part_src/tree/main/parts/oobb_part_oobb_tray_vertical_08_06_12/working)<br>[Oobb Part Oobb Tray Vertical 08 06 12](https://github.com/oomlout/oomlout_oomp_part_src/tree/main/parts/oobb_part_oobb_tray_vertical_08_06_12/working)<br><br>",
    "markdown_short": "[oobb_part_oobb_tray_vertical_08_06_12](https://github.com/oomlout/oomlout_oomp_part_src/tree/main/parts/oobb_part_oobb_tray_vertical_08_06_12/working)<br><br>"
}