{
    "classification": "oobb",
    "type": "part",
    "size": "oobb",
    "color": "",
    "description_main": "tray_vertical_02_02_15",
    "description_extra": "",
    "manufacturer": "",
    "part_number": "",
    "make_files": true,
    "short_name": "",
    "distributors": [],
    "classification_upper": "OOBB",
    "classification_capital": "Oobb",
    "classification_first_letter": "o",
    "classification_first_letter_upper": "O",
    "type_upper": "PART",
    "type_capital": "Part",
    "type_first_letter": "p",
    "type_first_letter_upper": "P",
    "size_upper": "OOBB",
    "size_capital": "Oobb",
    "size_first_letter": "o",
    "size_first_letter_upper": "O",
    "color_upper": "",
    "color_capital": "",
    "color_first_letter": "",
    "color_first_letter_upper": "",
    "description_main_upper": "TRAY_VERTICAL_02_02_15",
    "description_main_capital": "Tray Vertical 02 02.15",
    "description_main_first_letter": "t",
    "description_main_first_letter_upper": "T",
    "description_extra_upper": "",
    "description_extra_capital": "",
    "description_extra_first_letter": "",
    "description_extra_first_letter_upper": "",
    "manufacturer_upper": "",
    "manufacturer_capital": "",
    "manufacturer_first_letter": "",
    "manufacturer_first_letter_upper": "",
    "part_number_upper": "",
    "part_number_capital": "",
    "part_number_first_letter": "",
    "part_number_first_letter_upper": "",
    "id": "oobb_part_oobb_tray_vertical_02_02_15",
    "id_no_class": "part_tray_vertical_02_02_15",
    "id_no_type": "tray_vertical_02_02_15",
    "id_no_size": "tray_vertical_02_02_15",
    "oomp_key": "oomp_oobb_part_oobb_tray_vertical_02_02_15",
    "github_link": "https://github.com/oomlout/oomlout_oomp_part_src/tree/main/parts/oobb_part_oobb_tray_vertical_02_02_15/working",
    "directory": "parts/oobb_part_oobb_tray_vertical_02_02_15",
    "name": "Oobb Part Oobb Tray Vertical 02 02 15",
    "name_no_class": "Part Tray Vertical 02 02 15",
    "name_no_type": "Tray Vertical 02 02 15",
    "name_no_size": "Tray Vertical 02 02 15",
    "short_code": "ob",
    "short_code_upper": "OB",
    "manufacturers": [],
    "md5": "bac80b0cacb37394da5970caeea1340b",
    "md5_5": "bac80",
    "md5_5_upper": "BAC80",
    "md5_6": "bac80b",
    "md5_6_upper": "BAC80B",
    "md5_6_alpha": "7ad57",
    "md5_6_alpha_upper": "7AD57",
    "md5_10": "bac80b0cac",
    "md5_10_upper": "BAC80B0CAC",
    "oomp_word": "spaghetti apple sunglasses",
    "oomp_word_list": [
        "spaghetti",
        "apple",
        "sunglasses"
    ],
    "oomp_word_emoji": ":spaghetti: :apple: :sunglasses:",
    "oomp_word_emoji_list": [
        ":spaghetti:",
        ":apple:",
        ":sunglasses:"
    ],
    "size_only_numbers": "",
    "size_only_numbers_no_zeros": "",
    "description_only_numbers": "020215",
    "description_only_numbers_short": "20k",
    "name_no_size_short": "Tray Vertical 02 02 15",
    "description_or_color": "20k",
    "description_or_color_upper": "20K",
    "markdown_full": "[oobb_part_oobb_tray_vertical_02_02_15](https://github.com/oomlout/oomlout_oomp_part_src/tree/main/parts/oobb_part_oobb_tray_vertical_02_02_15/working)<br>[ob](https://github.com/oomlout/oomlout_oomp_part_src/tree/main/parts/oobb_part_oobb_tray_vertical_02_02_15/working)<br>[Oobb Part Oobb Tray Vertical 02 02 15](https://github.com/oomlout/oomlout_oomp_part_src/tree/main/parts/oobb_part_oobb_tray_vertical_02_02_15/working)<br><br>",
    "markdown_short": "[oobb_part_oobb_tray_vertical_02_02_15](https://github.com/oomlout/oomlout_oomp_part_src/tree/main/parts/oobb_part_oobb_tray_vertical_02_02_15/working)<br><br>"
}