{
    "classification": "oobb",
    "type": "part",
    "size": "shaft",
    "color": "",
    "description_main": "3d5_",
    "description_extra": "washer",
    "manufacturer": "",
    "part_number": "",
    "make_files": true,
    "short_name": "",
    "distributors": [],
    "classification_upper": "OOBB",
    "classification_capital": "Oobb",
    "classification_first_letter": "o",
    "classification_first_letter_upper": "O",
    "type_upper": "PART",
    "type_capital": "Part",
    "type_first_letter": "p",
    "type_first_letter_upper": "P",
    "size_upper": "SHAFT",
    "size_capital": "Shaft",
    "size_first_letter": "s",
    "size_first_letter_upper": "S",
    "color_upper": "",
    "color_capital": "",
    "color_first_letter": "",
    "color_first_letter_upper": "",
    "description_main_upper": "3D5_",
    "description_main_capital": "3D5 ",
    "description_main_first_letter": "3",
    "description_main_first_letter_upper": "3",
    "description_extra_upper": "WASHER",
    "description_extra_capital": "Washer",
    "description_extra_first_letter": "w",
    "description_extra_first_letter_upper": "W",
    "manufacturer_upper": "",
    "manufacturer_capital": "",
    "manufacturer_first_letter": "",
    "manufacturer_first_letter_upper": "",
    "part_number_upper": "",
    "part_number_capital": "",
    "part_number_first_letter": "",
    "part_number_first_letter_upper": "",
    "id": "oobb_part_shaft_3d5__washer",
    "id_no_class": "part_shaft_3d5__washer",
    "id_no_type": "shaft_3d5__washer",
    "id_no_size": "3d5__washer",
    "oomp_key": "oomp_oobb_part_shaft_3d5__washer",
    "github_link": "https://github.com/oomlout/oomlout_oomp_part_src/tree/main/parts/oobb_part_shaft_3d5__washer/working",
    "directory": "parts/oobb_part_shaft_3d5__washer",
    "name": "Oobb Part Shaft 3D5  Washer",
    "name_no_class": "Part Shaft 3D5  Washer",
    "name_no_type": "Shaft 3D5  Washer",
    "name_no_size": "3D5  Washer",
    "short_code": "",
    "short_code_upper": "",
    "manufacturers": [],
    "md5": "93f35a4501d8a55135babbf7b7a43601",
    "md5_5": "93f35",
    "md5_5_upper": "93F35",
    "md5_6": "93f35a",
    "md5_6_upper": "93F35A",
    "md5_6_alpha": "5rtju",
    "md5_6_alpha_upper": "5RTJU",
    "md5_10": "93f35a4501",
    "md5_10_upper": "93F35A4501",
    "oomp_word": "books two goat",
    "oomp_word_list": [
        "books",
        "two",
        "goat"
    ],
    "oomp_word_emoji": ":books: :two: :goat:",
    "oomp_word_emoji_list": [
        ":books:",
        ":two:",
        ":goat:"
    ],
    "size_only_numbers": "",
    "size_only_numbers_no_zeros": "",
    "description_only_numbers": "35",
    "description_only_numbers_short": "35",
    "name_no_size_short": "3D5  Washer",
    "description_or_color": "35",
    "description_or_color_upper": "35",
    "markdown_full": "[oobb_part_shaft_3d5__washer](https://github.com/oomlout/oomlout_oomp_part_src/tree/main/parts/oobb_part_shaft_3d5__washer/working)<br>[](https://github.com/oomlout/oomlout_oomp_part_src/tree/main/parts/oobb_part_shaft_3d5__washer/working)<br>[Oobb Part Shaft 3D5  Washer](https://github.com/oomlout/oomlout_oomp_part_src/tree/main/parts/oobb_part_shaft_3d5__washer/working)<br><br>",
    "markdown_short": "[oobb_part_shaft_3d5__washer](https://github.com/oomlout/oomlout_oomp_part_src/tree/main/parts/oobb_part_shaft_3d5__washer/working)<br><br>"
}