{
    "classification": "oobb",
    "type": "part",
    "size": "bolt",
    "color": "",
    "description_main": "hardware_bolt_m6_30",
    "description_extra": "",
    "manufacturer": "",
    "part_number": "",
    "make_files": true,
    "short_name": "",
    "distributors": [],
    "classification_upper": "OOBB",
    "classification_capital": "Oobb",
    "classification_first_letter": "o",
    "classification_first_letter_upper": "O",
    "type_upper": "PART",
    "type_capital": "Part",
    "type_first_letter": "p",
    "type_first_letter_upper": "P",
    "size_upper": "BOLT",
    "size_capital": "Bolt",
    "size_first_letter": "b",
    "size_first_letter_upper": "B",
    "color_upper": "",
    "color_capital": "",
    "color_first_letter": "",
    "color_first_letter_upper": "",
    "description_main_upper": "HARDWARE_BOLT_M6_30",
    "description_main_capital": "Hardware Bolt M6.30",
    "description_main_first_letter": "h",
    "description_main_first_letter_upper": "H",
    "description_extra_upper": "",
    "description_extra_capital": "",
    "description_extra_first_letter": "",
    "description_extra_first_letter_upper": "",
    "manufacturer_upper": "",
    "manufacturer_capital": "",
    "manufacturer_first_letter": "",
    "manufacturer_first_letter_upper": "",
    "part_number_upper": "",
    "part_number_capital": "",
    "part_number_first_letter": "",
    "part_number_first_letter_upper": "",
    "id": "oobb_part_bolt_hardware_bolt_m6_30",
    "id_no_class": "part_bolt_hardware_bolt_m6_30",
    "id_no_type": "bolt_hardware_bolt_m6_30",
    "id_no_size": "hardware_m6_30",
    "oomp_key": "oomp_oobb_part_bolt_hardware_bolt_m6_30",
    "github_link": "https://github.com/oomlout/oomlout_oomp_part_src/tree/main/parts/oobb_part_bolt_hardware_bolt_m6_30/working",
    "directory": "parts/oobb_part_bolt_hardware_bolt_m6_30",
    "name": "Oobb Part Bolt Hardware Bolt M6 30",
    "name_no_class": "Part Bolt Hardware Bolt M6 30",
    "name_no_type": "Bolt Hardware Bolt M6 30",
    "name_no_size": "Hardware M6 30",
    "short_code": "",
    "short_code_upper": "",
    "manufacturers": [],
    "md5": "70f6268e3369da9aaf2f785f54dbaa16",
    "md5_5": "70f62",
    "md5_5_upper": "70F62",
    "md5_6": "70f626",
    "md5_6_upper": "70F626",
    "md5_6_alpha": "4eo86",
    "md5_6_alpha_upper": "4EO86",
    "md5_10": "70f6268e33",
    "md5_10_upper": "70F6268E33",
    "oomp_word": "squirrel five eyes",
    "oomp_word_list": [
        "squirrel",
        "five",
        "eyes"
    ],
    "oomp_word_emoji": ":squirrel: :five: :eyes:",
    "oomp_word_emoji_list": [
        ":squirrel:",
        ":five:",
        ":eyes:"
    ],
    "size_only_numbers": "",
    "size_only_numbers_no_zeros": "",
    "description_only_numbers": "630",
    "description_only_numbers_short": "630",
    "name_no_size_short": "Hardware M6 30",
    "description_or_color": "630",
    "description_or_color_upper": "630",
    "markdown_full": "[oobb_part_bolt_hardware_bolt_m6_30](https://github.com/oomlout/oomlout_oomp_part_src/tree/main/parts/oobb_part_bolt_hardware_bolt_m6_30/working)<br>[](https://github.com/oomlout/oomlout_oomp_part_src/tree/main/parts/oobb_part_bolt_hardware_bolt_m6_30/working)<br>[Oobb Part Bolt Hardware Bolt M6 30](https://github.com/oomlout/oomlout_oomp_part_src/tree/main/parts/oobb_part_bolt_hardware_bolt_m6_30/working)<br><br>",
    "markdown_short": "[oobb_part_bolt_hardware_bolt_m6_30](https://github.com/oomlout/oomlout_oomp_part_src/tree/main/parts/oobb_part_bolt_hardware_bolt_m6_30/working)<br><br>"
}