{
    "classification": "oobb",
    "type": "part",
    "size": "plate",
    "color": "",
    "description_main": "14_05_03",
    "description_extra": "",
    "manufacturer": "",
    "part_number": "",
    "make_files": true,
    "short_name": "",
    "distributors": [],
    "classification_upper": "OOBB",
    "classification_capital": "Oobb",
    "classification_first_letter": "o",
    "classification_first_letter_upper": "O",
    "type_upper": "PART",
    "type_capital": "Part",
    "type_first_letter": "p",
    "type_first_letter_upper": "P",
    "size_upper": "PLATE",
    "size_capital": "Plate",
    "size_first_letter": "p",
    "size_first_letter_upper": "P",
    "color_upper": "",
    "color_capital": "",
    "color_first_letter": "",
    "color_first_letter_upper": "",
    "description_main_upper": "14_05_03",
    "description_main_capital": "14 05 03",
    "description_main_first_letter": "1",
    "description_main_first_letter_upper": "1",
    "description_extra_upper": "",
    "description_extra_capital": "",
    "description_extra_first_letter": "",
    "description_extra_first_letter_upper": "",
    "manufacturer_upper": "",
    "manufacturer_capital": "",
    "manufacturer_first_letter": "",
    "manufacturer_first_letter_upper": "",
    "part_number_upper": "",
    "part_number_capital": "",
    "part_number_first_letter": "",
    "part_number_first_letter_upper": "",
    "id": "oobb_part_plate_14_05_03",
    "id_no_class": "part_plate_14_05_03",
    "id_no_type": "plate_14_05_03",
    "id_no_size": "14_05_03",
    "oomp_key": "oomp_oobb_part_plate_14_05_03",
    "github_link": "https://github.com/oomlout/oomlout_oomp_part_src/tree/main/parts/oobb_part_plate_14_05_03/working",
    "directory": "parts/oobb_part_plate_14_05_03",
    "name": "Oobb Part Plate 14 05 03",
    "name_no_class": "Part Plate 14 05 03",
    "name_no_type": "Plate 14 05 03",
    "name_no_size": "14 05 03",
    "short_code": "",
    "short_code_upper": "",
    "manufacturers": [],
    "md5": "fca78b15fccf5747658a92e4c69ea161",
    "md5_5": "fca78",
    "md5_5_upper": "FCA78",
    "md5_6": "fca78b",
    "md5_6_upper": "FCA78B",
    "md5_6_alpha": "9uw7f",
    "md5_6_alpha_upper": "9UW7F",
    "md5_10": "fca78b15fc",
    "md5_10_upper": "FCA78B15FC",
    "oomp_word": "up guitar door",
    "oomp_word_list": [
        "up",
        "guitar",
        "door"
    ],
    "oomp_word_emoji": ":up: :guitar: :door:",
    "oomp_word_emoji_list": [
        ":up:",
        ":guitar:",
        ":door:"
    ],
    "size_only_numbers": "",
    "size_only_numbers_no_zeros": "",
    "description_only_numbers": "140503",
    "description_only_numbers_short": "141k",
    "name_no_size_short": "14 05 03",
    "description_or_color": "141k",
    "description_or_color_upper": "141K",
    "markdown_full": "[oobb_part_plate_14_05_03](https://github.com/oomlout/oomlout_oomp_part_src/tree/main/parts/oobb_part_plate_14_05_03/working)<br>[](https://github.com/oomlout/oomlout_oomp_part_src/tree/main/parts/oobb_part_plate_14_05_03/working)<br>[Oobb Part Plate 14 05 03](https://github.com/oomlout/oomlout_oomp_part_src/tree/main/parts/oobb_part_plate_14_05_03/working)<br><br>",
    "markdown_short": "[oobb_part_plate_14_05_03](https://github.com/oomlout/oomlout_oomp_part_src/tree/main/parts/oobb_part_plate_14_05_03/working)<br><br>"
}