{
    "classification": "oobb",
    "type": "part",
    "size": "gear",
    "color": "",
    "description_main": "02_03_",
    "description_extra": "16_teeth_sh_m3",
    "manufacturer": "",
    "part_number": "",
    "make_files": true,
    "short_name": "",
    "distributors": [],
    "classification_upper": "OOBB",
    "classification_capital": "Oobb",
    "classification_first_letter": "o",
    "classification_first_letter_upper": "O",
    "type_upper": "PART",
    "type_capital": "Part",
    "type_first_letter": "p",
    "type_first_letter_upper": "P",
    "size_upper": "GEAR",
    "size_capital": "Gear",
    "size_first_letter": "g",
    "size_first_letter_upper": "G",
    "color_upper": "",
    "color_capital": "",
    "color_first_letter": "",
    "color_first_letter_upper": "",
    "description_main_upper": "02_03_",
    "description_main_capital": "02 03 ",
    "description_main_first_letter": "0",
    "description_main_first_letter_upper": "0",
    "description_extra_upper": "16_TEETH_SH_M3",
    "description_extra_capital": "16 Teeth Sh M3",
    "description_extra_first_letter": "1",
    "description_extra_first_letter_upper": "1",
    "manufacturer_upper": "",
    "manufacturer_capital": "",
    "manufacturer_first_letter": "",
    "manufacturer_first_letter_upper": "",
    "part_number_upper": "",
    "part_number_capital": "",
    "part_number_first_letter": "",
    "part_number_first_letter_upper": "",
    "id": "oobb_part_gear_02_03__16_teeth_sh_m3",
    "id_no_class": "part_gear_02_03__16_teeth_sh_m3",
    "id_no_type": "gear_02_03__16_teeth_sh_m3",
    "id_no_size": "02_03__16_teeth_sh_m3",
    "oomp_key": "oomp_oobb_part_gear_02_03__16_teeth_sh_m3",
    "github_link": "https://github.com/oomlout/oomlout_oomp_part_src/tree/main/parts/oobb_part_gear_02_03__16_teeth_sh_m3/working",
    "directory": "parts/oobb_part_gear_02_03__16_teeth_sh_m3",
    "name": "Oobb Part Gear 02 03  16 Teeth Sh M3",
    "name_no_class": "Part Gear 02 03  16 Teeth Sh M3",
    "name_no_type": "Gear 02 03  16 Teeth Sh M3",
    "name_no_size": "02 03  16 Teeth Sh M3",
    "short_code": "",
    "short_code_upper": "",
    "manufacturers": [],
    "md5": "25e2c2a0c82a001e5a52da1f5d7373b6",
    "md5_5": "25e2c",
    "md5_5_upper": "25E2C",
    "md5_6": "25e2c2",
    "md5_6_upper": "25E2C2",
    "md5_6_alpha": "1h7sy",
    "md5_6_alpha_upper": "1H7SY",
    "md5_10": "25e2c2a0c8",
    "md5_10_upper": "25E2C2A0C8",
    "oomp_word": "ear sailboat birthday",
    "oomp_word_list": [
        "ear",
        "sailboat",
        "birthday"
    ],
    "oomp_word_emoji": ":ear: :sailboat: :birthday:",
    "oomp_word_emoji_list": [
        ":ear:",
        ":sailboat:",
        ":birthday:"
    ],
    "size_only_numbers": "",
    "size_only_numbers_no_zeros": "",
    "description_only_numbers": "0203",
    "description_only_numbers_short": "203",
    "name_no_size_short": "02 03  16 Teeth Sh M3",
    "description_or_color": "203",
    "description_or_color_upper": "203",
    "markdown_full": "[oobb_part_gear_02_03__16_teeth_sh_m3](https://github.com/oomlout/oomlout_oomp_part_src/tree/main/parts/oobb_part_gear_02_03__16_teeth_sh_m3/working)<br>[](https://github.com/oomlout/oomlout_oomp_part_src/tree/main/parts/oobb_part_gear_02_03__16_teeth_sh_m3/working)<br>[Oobb Part Gear 02 03  16 Teeth Sh M3](https://github.com/oomlout/oomlout_oomp_part_src/tree/main/parts/oobb_part_gear_02_03__16_teeth_sh_m3/working)<br><br>",
    "markdown_short": "[oobb_part_gear_02_03__16_teeth_sh_m3](https://github.com/oomlout/oomlout_oomp_part_src/tree/main/parts/oobb_part_gear_02_03__16_teeth_sh_m3/working)<br><br>"
}